[
  {
    "line": 2,
    "elements": [
      {
        "before": [
          {
            "result": {
              "duration": 1563360500,
              "status": "passed"
            },
            "match": {
              "location": "Hooks.setup()"
            }
          }
        ],
        "line": 28,
        "name": "Connexion OK",
        "description": "",
        "id": "connexion-us2;connexion-ok;;2",
        "type": "scenario",
        "keyword": "Scenario Outline",
        "steps": [
          {
            "result": {
              "duration": 5777272500,
              "status": "passed"
            },
            "line": 21,
            "name": "je clique sur la page My Account",
            "match": {
              "location": "MyStepdefsAcceuil.jeCliqueSurLaPageMyAccount()"
            },
            "keyword": "Given "
          },
          {
            "result": {
              "duration": 73994900,
              "status": "passed"
            },
            "line": 22,
            "name": "dans la page login je saisie le mail dans le champ mail  \"fatiha-m_18@hotmail.com\"",
            "match": {
              "arguments": [
                {
                  "val": "\"fatiha-m_18@hotmail.com\"",
                  "offset": 57
                }
              ],
              "location": "MyStepdefsMyAccount.dansLaPageLoginJeSaisieLeMailDansLeChampMail(String)"
            },
            "keyword": "When "
          },
          {
            "result": {
              "duration": 164739600,
              "status": "passed"
            },
            "line": 23,
            "name": "dans la page login je saisie le MDP dans le champ MDP \"Anir1234\u0026\"",
            "match": {
              "arguments": [
                {
                  "val": "\"Anir1234\u0026\"",
                  "offset": 54
                }
              ],
              "location": "MyStepdefsMyAccount.dansLaPageLoginJeSaisieLeMDPDansLeChampMDP(String)"
            },
            "keyword": "And "
          },
          {
            "result": {
              "duration": 912201600,
              "status": "passed"
            },
            "line": 24,
            "name": "je clique sur le bouton LOGIN",
            "match": {
              "location": "MyStepdefsMyAccount.jeCliqueSurLeBoutonLOGIN()"
            },
            "keyword": "And "
          },
          {
            "result": {
              "duration": 32590900,
              "status": "passed"
            },
            "line": 25,
            "name": "je vérifie que l\u0027écran Dashboard est affiché",
            "match": {
              "location": "MyStepdefsMyAccount.jeVérifieQueLÉcranDashboardEstAffiché()"
            },
            "keyword": "Then "
          }
        ],
        "tags": [
          {
            "name": "@REQ_POEC3-2"
          },
          {
            "name": "@TEST_POEC3-22"
          },
          {
            "name": "@Fatiha_test"
          }
        ]
      }
    ],
    "name": "Connexion US2",
    "description": "",
    "id": "connexion-us2",
    "keyword": "Feature",
    "uri": "classpath:TestConnexionOK.feature",
    "tags": [
      {
        "name": "@REQ_POEC3-2",
        "type": "Tag",
        "location": {
          "line": 1,
          "column": 1
        }
      }
    ]
  }
]